{
	"definitions": {},
	"$schema": "http://json-schema.org/draft-07/schema#", 
	"$id": "https://example.com/object1676761034.json", 
	"title": "Root", 
	"type": "array",
	"default": [],
	"items":{
		"$id": "#root/items", 
		"title": "Items", 
		"type": "object",
		"required": [
			"name",
			"hash"
		],
		"properties": {
			"name": {
				"$id": "#root/items/name", 
				"title": "Name", 
				"type": "string",
				"default": "",
				"examples": [
					"blip_ambient_bounty_hunter"
				],
				"pattern": "^.*$"
			},
			"hash": {
				"$id": "#root/items/hash", 
				"title": "Hash", 
				"type": "integer",
				"examples": [
					-861219276
				],
				"default": 0
			}
		}
	}

}